meetcount_cli/__init__.py
meetcount_cli/config/__init__.py
meetcount_cli/config/__pycache__/__init__.cpython-312.pyc
meetcount_cli/config/__pycache__/typedef.cpython-312.pyc
meetcount_cli/config/files/docker-compose.yml
meetcount_cli/config/files/variables.env
meetcount_cli/config/typedef.py
meetcount_cli/core/__init__.py
meetcount_cli/core/__pycache__/__init__.cpython-312.pyc
meetcount_cli/core/__pycache__/options.cpython-312.pyc
meetcount_cli/core/__pycache__/validators.cpython-312.pyc
meetcount_cli/core/options.py
meetcount_cli/core/validators.py
meetcount_cli/main.py
meetcount_cli-0.1.15.dist-info/METADATA
meetcount_cli-0.1.15.dist-info/WHEEL
meetcount_cli-0.1.15.dist-info/entry_points.txt
meetcount_cli-0.1.15.dist-info/RECORD
