Metadata-Version: 2.3
Name: meetcount-cli
Version: 0.1.15
Summary: 
Author: et.abbey
Author-email: abbeyemmanueltetteh@gmail.com
Requires-Python: >=3.12
Classifier: Programming Language :: Python :: 3
Classifier: Programming Language :: Python :: 3.12
Classifier: Programming Language :: Python :: 3.13
Requires-Dist: certbot (>=3.1.0,<4.0.0)
Requires-Dist: typer (>=0.15.1,<0.16.0)
